<?xml version="1.0" encoding="utf-8"?>
<AanleveringInformatieObject xmlns="https://standaarden.overheid.nl/lvbb/stop/aanlevering/"
                             xmlns:geo="https://standaarden.overheid.nl/stop/imop/geo/"
                             xmlns:xsi="http://www.w3.org/2001/XMLSchema-instance"
                             schemaversie="1.2.0"
                             xsi:schemaLocation="https://standaarden.overheid.nl/lvbb/stop/aanlevering https://standaarden.overheid.nl/lvbb/1.2.0/lvbb-stop-aanlevering.xsd">
   <InformatieObjectVersie>
      <ExpressionIdentificatie xmlns="https://standaarden.overheid.nl/stop/imop/data/">
         <FRBRWork>/join/id/regdata/gm0363/2022/1a_PuntengroepOngewijzigd_2</FRBRWork>
         <FRBRExpression>/join/id/regdata/gm0363/2022/1a_PuntengroepOngewijzigd_2/nld@2022;1</FRBRExpression>
         <soortWork>/join/id/stop/work_010</soortWork>
      </ExpressionIdentificatie>
      <InformatieObjectVersieMetadata xmlns="https://standaarden.overheid.nl/stop/imop/data/">
         <heeftGeboorteregeling>/akn/nl/act/gm0363/2022/TijdreisPlanRegelstructuurNieuw</heeftGeboorteregeling>
         <heeftBestanden>
            <heeftBestand>
               <Bestand>
                  <bestandsnaam>PuntengroepOngewijzigd.gml</bestandsnaam>
                  <hash>1a2675ed93ca5b05d4ea19c26188be15660d5d06510208d2e172410fd6aaf3755bb8081931d477eb41d879493dde7b7517b0cc2d1753791ad5ea4e9ddc98c3fb</hash>
               </Bestand>
            </heeftBestand>
         </heeftBestanden>
      </InformatieObjectVersieMetadata>
      <InformatieObjectMetadata xmlns="https://standaarden.overheid.nl/stop/imop/data/">
         <eindverantwoordelijke>/tooi/id/gemeente/gm0363</eindverantwoordelijke>
         <maker>/tooi/id/gemeente/gm0363</maker>
         <alternatieveTitels>
            <alternatieveTitel/>
         </alternatieveTitels>
         <officieleTitel>/join/id/regdata/gm0363/2022/1a_PuntengroepOngewijzigd_2</officieleTitel>
         <publicatieinstructie>TeConsolideren</publicatieinstructie>
         <formaatInformatieobject>/join/id/stop/informatieobject/gio_002</formaatInformatieobject>
         <naamInformatieObject>PuntengroepOngewijzigd
</naamInformatieObject>
      </InformatieObjectMetadata>
   </InformatieObjectVersie>
</AanleveringInformatieObject>
