<?xml version="1.0" encoding="utf-8"?>
<AanleveringInformatieObject xmlns="https://standaarden.overheid.nl/lvbb/stop/aanlevering/"
                             xmlns:geo="https://standaarden.overheid.nl/stop/imop/geo/"
                             xmlns:xsi="http://www.w3.org/2001/XMLSchema-instance"
                             schemaversie="1.2.0"
                             xsi:schemaLocation="https://standaarden.overheid.nl/lvbb/stop/aanlevering https://standaarden.overheid.nl/lvbb/1.2.0/lvbb-stop-aanlevering.xsd">
   <InformatieObjectVersie>
      <ExpressionIdentificatie xmlns="https://standaarden.overheid.nl/stop/imop/data/">
         <FRBRWork>/join/id/regdata/gm0363/2022/PuntengroepIntrekkenVervangen_2</FRBRWork>
         <FRBRExpression>/join/id/regdata/gm0363/2022/PuntengroepIntrekkenVervangen_2/nld@2022;1</FRBRExpression>
         <soortWork>/join/id/stop/work_010</soortWork>
      </ExpressionIdentificatie>
      <InformatieObjectVersieMetadata xmlns="https://standaarden.overheid.nl/stop/imop/data/">
         <heeftGeboorteregeling>/akn/nl/act/gm0363/2022/RegelingAmsterdam</heeftGeboorteregeling>
         <heeftBestanden>
            <heeftBestand>
               <Bestand>
                  <bestandsnaam>PuntengroepIntrekkenVervangen.gml</bestandsnaam>
                  <hash>cd3cee69192d84d8f8c86ee3c9974423fcec3de5a464c01694a8c3d72f5184d52ba622489a8998abb7ac575c49c8c5c56bbafb757d0eeb2e613ec624d90dbb94</hash>
               </Bestand>
            </heeftBestand>
         </heeftBestanden>
      </InformatieObjectVersieMetadata>
      <InformatieObjectMetadata xmlns="https://standaarden.overheid.nl/stop/imop/data/">
         <eindverantwoordelijke>/tooi/id/gemeente/gm0363</eindverantwoordelijke>
         <maker>/tooi/id/gemeente/gm0363</maker>
         <alternatieveTitels>
            <alternatieveTitel/>
         </alternatieveTitels>
         <officieleTitel>/join/id/regdata/gm0363/2022/PuntengroepIntrekkenVervangen_2</officieleTitel>
         <publicatieinstructie>TeConsolideren</publicatieinstructie>
         <formaatInformatieobject>/join/id/stop/informatieobject/gio_002</formaatInformatieobject>
         <naamInformatieObject>PuntengroepIntrekkenVervangen</naamInformatieObject>
      </InformatieObjectMetadata>
   </InformatieObjectVersie>
</AanleveringInformatieObject>
